{
    "id": "2aae629ea969e168f668913bd25f09b4",
    "name": "Anzahlungen auf immaterielle Verm\u00f6gensgegenst\u00e4nde",
    "type": "Aktiva",
    "code": "0039",
    "sort-code": 39,
    "description": "Geleistete Anzahlungen auf immaterielleVerm\u00f6gensgegenst\u00e4nde",
    "categories": [
        "0038-0039 Geleistete Anzahlungen",
        "0010-0049 Immaterielle Verm\u00f6gensgegenst\u00e4nde",
        "0010-0249 ANLAGEVERM\u00d6GEN",
        "0 aktive Verm\u00f6gensposten"
    ],
    "leaf": true,
    "hierarchicalCategories.lvl3": "0 aktive Verm\u00f6gensposten > 0010-0249 ANLAGEVERM\u00d6GEN > 0010-0049 Immaterielle Verm\u00f6gensgegenst\u00e4nde > 0038-0039 Geleistete Anzahlungen",
    "hierarchicalCategories.lvl2": "0 aktive Verm\u00f6gensposten > 0010-0249 ANLAGEVERM\u00d6GEN > 0010-0049 Immaterielle Verm\u00f6gensgegenst\u00e4nde",
    "hierarchicalCategories.lvl1": "0 aktive Verm\u00f6gensposten > 0010-0249 ANLAGEVERM\u00d6GEN",
    "hierarchicalCategories.lvl0": "0 aktive Verm\u00f6gensposten",
    "parent": "61196055f04cd567208a3a828d895627"
}