{
    "id": "2f5d6ae129bc46f2cd0cb4884e018103",
    "name": "Sonderposten mit R\u00fccklageanteil",
    "type": "Fremdkapital",
    "code": "1180",
    "sort-code": 1180,
    "description": "Sonderposten mit R\u00fccklageanteil",
    "categories": [
        "1180-1199 SONDERPOSTEN",
        "1 passive Verm\u00f6gensposten"
    ],
    "leaf": true,
    "hierarchicalCategories.lvl1": "1 passive Verm\u00f6gensposten > 1180-1199 SONDERPOSTEN",
    "hierarchicalCategories.lvl0": "1 passive Verm\u00f6gensposten",
    "parent": "79838dac3d7a259a0d0226ba63c65a62"
}