{
    "objectID": "6920a25ebaea76f7b457244d238a3f2c",
    "name": "0866 Vorsteuer aus Erwerb als letzter Abnehmer innerhalb eines Dreiecksgesch\u00e4fts",
    "type": "Aktiva",
    "code": "0866",
    "description": "Vorsteuer aus Erwerb als letzter Abnehmer innerhalb eines Dreiecksgesch\u00e4fts",
    "categories": [
        "0730-0866 Umsatzsteuer-Konten",
        "0700 Sonstige Verm\u00f6gensgegenst\u00e4nde",
        "0650-0899 Forderungen, sonstige Verm\u00f6gensgegenst\u00e4nde",
        "0600-0989 UMLAUFVERM\u00d6GEN",
        "0 aktive Verm\u00f6gensposten"
    ],
    "hierarchicalCategories": [
        {
            "lvl4": "0 aktive Verm\u00f6gensposten > 0600-0989 UMLAUFVERM\u00d6GEN > 0650-0899 Forderungen, sonstige Verm\u00f6gensgegenst\u00e4nde > 0700 Sonstige Verm\u00f6gensgegenst\u00e4nde > 0730-0866 Umsatzsteuer-Konten"
        },
        {
            "lvl3": "0 aktive Verm\u00f6gensposten > 0600-0989 UMLAUFVERM\u00d6GEN > 0650-0899 Forderungen, sonstige Verm\u00f6gensgegenst\u00e4nde > 0700 Sonstige Verm\u00f6gensgegenst\u00e4nde"
        },
        {
            "lvl2": "0 aktive Verm\u00f6gensposten > 0600-0989 UMLAUFVERM\u00d6GEN > 0650-0899 Forderungen, sonstige Verm\u00f6gensgegenst\u00e4nde"
        },
        {
            "lvl1": "0 aktive Verm\u00f6gensposten > 0600-0989 UMLAUFVERM\u00d6GEN"
        },
        {
            "lvl0": "0 aktive Verm\u00f6gensposten"
        }
    ],
    "leaf": true,
    "notes": "Sammelkonto\n\u00dcberschu\u00dfrechner \u2013 keine Zuordnung",
    "parent": "d77dae85fa3d5687d5749baca6a2a149"
}