{
    "id": "cea49bf0978da68c23e35208fc0cfe1e",
    "name": "Nicht abziehbare Vorsteuer",
    "type": "Aufwand",
    "code": "2903",
    "sort-code": 2903,
    "description": "Nicht abziehbare Vorsteuer",
    "categories": [
        "2903-2904 Umsatzsteuer",
        "2903-2945 Umsatzsteuer-Konten",
        "2510 \u00dcbrige Ausgaben",
        "2500-2999 AUSGABEN",
        "2 Erfolgskonten ideeller Bereich"
    ],
    "leaf": true,
    "hierarchicalCategories.lvl4": "2 Erfolgskonten ideeller Bereich > 2500-2999 AUSGABEN > 2510 \u00dcbrige Ausgaben > 2903-2945 Umsatzsteuer-Konten > 2903-2904 Umsatzsteuer",
    "hierarchicalCategories.lvl3": "2 Erfolgskonten ideeller Bereich > 2500-2999 AUSGABEN > 2510 \u00dcbrige Ausgaben > 2903-2945 Umsatzsteuer-Konten",
    "hierarchicalCategories.lvl2": "2 Erfolgskonten ideeller Bereich > 2500-2999 AUSGABEN > 2510 \u00dcbrige Ausgaben",
    "hierarchicalCategories.lvl1": "2 Erfolgskonten ideeller Bereich > 2500-2999 AUSGABEN",
    "hierarchicalCategories.lvl0": "2 Erfolgskonten ideeller Bereich",
    "parent": "f9ef7e9d03b48a7e1925ad30ff5da4d4"
}