{
    "id": "d6b0483f454d9fb7a78e3f3f4f166423",
    "name": "AUSGABEN / AUFWENDUNGEN",
    "type": "Aufwand",
    "code": "6170-6499",
    "sort-code": 9999,
    "description": "AUSGABEN / AUFWENDUNGEN",
    "categories": [
        "6000-6499 SONSTIGE ZWECKBETRIEBE 1",
        "6000-6989 SONSTIGE ZWECKBETRIEBE",
        "6 Erfolgskonten f\u00fcr andere ertragssteuerfreie Zweckbetriebe"
    ],
    "leaf": false,
    "hierarchicalCategories.lvl2": "6 Erfolgskonten f\u00fcr andere ertragssteuerfreie Zweckbetriebe > 6000-6989 SONSTIGE ZWECKBETRIEBE > 6000-6499 SONSTIGE ZWECKBETRIEBE 1",
    "hierarchicalCategories.lvl1": "6 Erfolgskonten f\u00fcr andere ertragssteuerfreie Zweckbetriebe > 6000-6989 SONSTIGE ZWECKBETRIEBE",
    "hierarchicalCategories.lvl0": "6 Erfolgskonten f\u00fcr andere ertragssteuerfreie Zweckbetriebe",
    "placeholder": true,
    "parent": "288c7514c7b4037536f094a8aff9858a"
}