{
    "objectID": "ec02c72129e370331ab9bf07579e54af",
    "name": "6060 Sonstige betriebliche Ertr\u00e4ge",
    "type": "Ertrag",
    "code": "6060",
    "description": "Sonstige betriebliche Ertr\u00e4ge",
    "categories": [
        "6000-6099 EINNAHMEN / ERTR\u00c4GE",
        "6000-6499 SONSTIGE ZWECKBETRIEBE 1",
        "6000-6989 SONSTIGE ZWECKBETRIEBE",
        "6 Erfolgskonten f\u00fcr andere ertragssteuerfreie Zweckbetriebe"
    ],
    "hierarchicalCategories": [
        {
            "lvl3": "6 Erfolgskonten f\u00fcr andere ertragssteuerfreie Zweckbetriebe > 6000-6989 SONSTIGE ZWECKBETRIEBE > 6000-6499 SONSTIGE ZWECKBETRIEBE 1 > 6000-6099 EINNAHMEN / ERTR\u00c4GE"
        },
        {
            "lvl2": "6 Erfolgskonten f\u00fcr andere ertragssteuerfreie Zweckbetriebe > 6000-6989 SONSTIGE ZWECKBETRIEBE > 6000-6499 SONSTIGE ZWECKBETRIEBE 1"
        },
        {
            "lvl1": "6 Erfolgskonten f\u00fcr andere ertragssteuerfreie Zweckbetriebe > 6000-6989 SONSTIGE ZWECKBETRIEBE"
        },
        {
            "lvl0": "6 Erfolgskonten f\u00fcr andere ertragssteuerfreie Zweckbetriebe"
        }
    ],
    "leaf": true,
    "parent": "5bd13af9c0ac04dd2b9244bfe651f412"
}