{
    "objectID": "03b3ecc4f42d4e35b82a8531ae2c62a8",
    "name": "Ertr\u00e4ge aus der steuerlich niedrigeren Bewertung von Verbindlichkeiten",
    "type": "Ertrag",
    "code": "4933",
    "description": "",
    "categories": [
        "04. Sonstige betriebliche Ertr\u00e4ge"
    ],
    "hierarchicalCategories": [
        {
            "lvl0": "04. Sonstige betriebliche Ertr\u00e4ge"
        }
    ],
    "leaf": true,
    "placeholder": false,
    "parent": "4c0c1557fe54e71d7ed717587a0c0b4d"
}