{
    "objectID": "4b94caba6927babf0af628999af0e00d",
    "name": "04. Geleistete Anzahlungen auf Vorr\u00e4te",
    "type": "Aktiva",
    "code": "1180",
    "description": "",
    "categories": [
        "I. Vorr\u00e4te",
        "B. Umlaufverm\u00f6gen",
        "Aktiva"
    ],
    "hierarchicalCategories": [
        {
            "lvl2": "Aktiva > B. Umlaufverm\u00f6gen > I. Vorr\u00e4te"
        },
        {
            "lvl1": "Aktiva > B. Umlaufverm\u00f6gen"
        },
        {
            "lvl0": "Aktiva"
        }
    ],
    "leaf": true,
    "placeholder": true,
    "parent": "693674f6bcdd8dfbc525267340f4771b"
}