{
    "id": "e3d893eba2e242ef3aa418d8226f2805",
    "name": "Verbindlichk. Verm\u00f6gensbildung (1-5 J)",
    "type": "Verbindlichkeit",
    "code": "3780",
    "sort-code": 3780,
    "description": "",
    "categories": [
        "Verbindlichkeiten aus Verm\u00f6gensbildung",
        "08. sonstige Verbindlichkeiten",
        "C. Verbindlichkeiten",
        "Passiva"
    ],
    "leaf": true,
    "hierarchicalCategories.lvl3": "Passiva > C. Verbindlichkeiten > 08. sonstige Verbindlichkeiten > Verbindlichkeiten aus Verm\u00f6gensbildung",
    "hierarchicalCategories.lvl2": "Passiva > C. Verbindlichkeiten > 08. sonstige Verbindlichkeiten",
    "hierarchicalCategories.lvl1": "Passiva > C. Verbindlichkeiten",
    "hierarchicalCategories.lvl0": "Passiva",
    "placeholder": false,
    "parent": "34fc3612b13809ba551d2e11b0f5dad2"
}